{
  "id": "6fcff429-1202-4122-bcc4-5f5b1dec42d3",
  "prevId": "00000000-0000-0000-0000-000000000000",
  "version": "7",
  "dialect": "postgresql",
  "tables": {
    "public.action_items": {
      "name": "action_items",
      "schema": "",
      "columns": {
        "id": {
          "name": "id",
          "type": "uuid",
          "primaryKey": true,
          "notNull": true,
          "default": "gen_random_uuid()"
        },
        "user_id": {
          "name": "user_id",
          "type": "uuid",
          "primaryKey": false,
          "notNull": true
        },
        "meeting_cache_id": {
          "name": "meeting_cache_id",
          "type": "uuid",
          "primaryKey": false,
          "notNull": false
        },
        "title": {
          "name": "title",
          "type": "varchar(512)",
          "primaryKey": false,
          "notNull": true
        },
        "description": {
          "name": "description",
          "type": "text",
          "primaryKey": false,
          "notNull": false
        },
        "assignee": {
          "name": "assignee",
          "type": "varchar(256)",
          "primaryKey": false,
          "notNull": false
        },
        "assignee_email": {
          "name": "assignee_email",
          "type": "varchar(320)",
          "primaryKey": false,
          "notNull": false
        },
        "due_date": {
          "name": "due_date",
          "type": "timestamp with time zone",
          "primaryKey": false,
          "notNull": false
        },
        "priority": {
          "name": "priority",
          "type": "varchar(20)",
          "primaryKey": false,
          "notNull": false,
          "default": "'medium'"
        },
        "context": {
          "name": "context",
          "type": "text",
          "primaryKey": false,
          "notNull": false
        },
        "task_created": {
          "name": "task_created",
          "type": "boolean",
          "primaryKey": false,
          "notNull": false,
          "default": false
        },
        "task_platform": {
          "name": "task_platform",
          "type": "platform",
          "typeSchema": "public",
          "primaryKey": false,
          "notNull": false
        },
        "task_external_id": {
          "name": "task_external_id",
          "type": "varchar(256)",
          "primaryKey": false,
          "notNull": false
        },
        "task_url": {
          "name": "task_url",
          "type": "text",
          "primaryKey": false,
          "notNull": false
        },
        "status": {
          "name": "status",
          "type": "varchar(50)",
          "primaryKey": false,
          "notNull": false,
          "default": "'pending'"
        },
        "created_at": {
          "name": "created_at",
          "type": "timestamp with time zone",
          "primaryKey": false,
          "notNull": true,
          "default": "now()"
        },
        "updated_at": {
          "name": "updated_at",
          "type": "timestamp with time zone",
          "primaryKey": false,
          "notNull": true,
          "default": "now()"
        }
      },
      "indexes": {
        "action_items_user_idx": {
          "name": "action_items_user_idx",
          "columns": [
            {
              "expression": "user_id",
              "isExpression": false,
              "asc": true,
              "nulls": "last"
            }
          ],
          "isUnique": false,
          "concurrently": false,
          "method": "btree",
          "with": {}
        },
        "action_items_meeting_idx": {
          "name": "action_items_meeting_idx",
          "columns": [
            {
              "expression": "meeting_cache_id",
              "isExpression": false,
              "asc": true,
              "nulls": "last"
            }
          ],
          "isUnique": false,
          "concurrently": false,
          "method": "btree",
          "with": {}
        },
        "action_items_status_idx": {
          "name": "action_items_status_idx",
          "columns": [
            {
              "expression": "status",
              "isExpression": false,
              "asc": true,
              "nulls": "last"
            }
          ],
          "isUnique": false,
          "concurrently": false,
          "method": "btree",
          "with": {}
        }
      },
      "foreignKeys": {
        "action_items_user_id_users_id_fk": {
          "name": "action_items_user_id_users_id_fk",
          "tableFrom": "action_items",
          "tableTo": "users",
          "columnsFrom": [
            "user_id"
          ],
          "columnsTo": [
            "id"
          ],
          "onDelete": "cascade",
          "onUpdate": "no action"
        },
        "action_items_meeting_cache_id_meetings_cache_id_fk": {
          "name": "action_items_meeting_cache_id_meetings_cache_id_fk",
          "tableFrom": "action_items",
          "tableTo": "meetings_cache",
          "columnsFrom": [
            "meeting_cache_id"
          ],
          "columnsTo": [
            "id"
          ],
          "onDelete": "set null",
          "onUpdate": "no action"
        }
      },
      "compositePrimaryKeys": {},
      "uniqueConstraints": {},
      "policies": {},
      "checkConstraints": {},
      "isRLSEnabled": false
    },
    "public.audit_log": {
      "name": "audit_log",
      "schema": "",
      "columns": {
        "id": {
          "name": "id",
          "type": "uuid",
          "primaryKey": true,
          "notNull": true,
          "default": "gen_random_uuid()"
        },
        "user_id": {
          "name": "user_id",
          "type": "uuid",
          "primaryKey": false,
          "notNull": false
        },
        "event_type": {
          "name": "event_type",
          "type": "varchar(100)",
          "primaryKey": false,
          "notNull": true
        },
        "event_category": {
          "name": "event_category",
          "type": "varchar(50)",
          "primaryKey": false,
          "notNull": true
        },
        "resource_type": {
          "name": "resource_type",
          "type": "varchar(100)",
          "primaryKey": false,
          "notNull": false
        },
        "resource_id": {
          "name": "resource_id",
          "type": "varchar(256)",
          "primaryKey": false,
          "notNull": false
        },
        "description": {
          "name": "description",
          "type": "text",
          "primaryKey": false,
          "notNull": false
        },
        "metadata": {
          "name": "metadata",
          "type": "jsonb",
          "primaryKey": false,
          "notNull": false,
          "default": "'{}'::jsonb"
        },
        "ip_address": {
          "name": "ip_address",
          "type": "varchar(45)",
          "primaryKey": false,
          "notNull": false
        },
        "user_agent": {
          "name": "user_agent",
          "type": "text",
          "primaryKey": false,
          "notNull": false
        },
        "success": {
          "name": "success",
          "type": "boolean",
          "primaryKey": false,
          "notNull": false,
          "default": true
        },
        "error_message": {
          "name": "error_message",
          "type": "text",
          "primaryKey": false,
          "notNull": false
        },
        "created_at": {
          "name": "created_at",
          "type": "timestamp with time zone",
          "primaryKey": false,
          "notNull": true,
          "default": "now()"
        }
      },
      "indexes": {
        "audit_log_user_idx": {
          "name": "audit_log_user_idx",
          "columns": [
            {
              "expression": "user_id",
              "isExpression": false,
              "asc": true,
              "nulls": "last"
            }
          ],
          "isUnique": false,
          "concurrently": false,
          "method": "btree",
          "with": {}
        },
        "audit_log_event_type_idx": {
          "name": "audit_log_event_type_idx",
          "columns": [
            {
              "expression": "event_type",
              "isExpression": false,
              "asc": true,
              "nulls": "last"
            }
          ],
          "isUnique": false,
          "concurrently": false,
          "method": "btree",
          "with": {}
        },
        "audit_log_created_at_idx": {
          "name": "audit_log_created_at_idx",
          "columns": [
            {
              "expression": "created_at",
              "isExpression": false,
              "asc": true,
              "nulls": "last"
            }
          ],
          "isUnique": false,
          "concurrently": false,
          "method": "btree",
          "with": {}
        }
      },
      "foreignKeys": {
        "audit_log_user_id_users_id_fk": {
          "name": "audit_log_user_id_users_id_fk",
          "tableFrom": "audit_log",
          "tableTo": "users",
          "columnsFrom": [
            "user_id"
          ],
          "columnsTo": [
            "id"
          ],
          "onDelete": "set null",
          "onUpdate": "no action"
        }
      },
      "compositePrimaryKeys": {},
      "uniqueConstraints": {},
      "policies": {},
      "checkConstraints": {},
      "isRLSEnabled": false
    },
    "public.meetings_cache": {
      "name": "meetings_cache",
      "schema": "",
      "columns": {
        "id": {
          "name": "id",
          "type": "uuid",
          "primaryKey": true,
          "notNull": true,
          "default": "gen_random_uuid()"
        },
        "user_id": {
          "name": "user_id",
          "type": "uuid",
          "primaryKey": false,
          "notNull": true
        },
        "platform": {
          "name": "platform",
          "type": "platform",
          "typeSchema": "public",
          "primaryKey": false,
          "notNull": true
        },
        "platform_meeting_id": {
          "name": "platform_meeting_id",
          "type": "varchar(256)",
          "primaryKey": false,
          "notNull": true
        },
        "title": {
          "name": "title",
          "type": "varchar(512)",
          "primaryKey": false,
          "notNull": false
        },
        "start_time": {
          "name": "start_time",
          "type": "timestamp with time zone",
          "primaryKey": false,
          "notNull": false
        },
        "end_time": {
          "name": "end_time",
          "type": "timestamp with time zone",
          "primaryKey": false,
          "notNull": false
        },
        "duration_minutes": {
          "name": "duration_minutes",
          "type": "integer",
          "primaryKey": false,
          "notNull": false
        },
        "participant_count": {
          "name": "participant_count",
          "type": "integer",
          "primaryKey": false,
          "notNull": false
        },
        "participants": {
          "name": "participants",
          "type": "jsonb",
          "primaryKey": false,
          "notNull": false
        },
        "has_recording": {
          "name": "has_recording",
          "type": "boolean",
          "primaryKey": false,
          "notNull": false,
          "default": false
        },
        "has_transcript": {
          "name": "has_transcript",
          "type": "boolean",
          "primaryKey": false,
          "notNull": false,
          "default": false
        },
        "metadata": {
          "name": "metadata",
          "type": "jsonb",
          "primaryKey": false,
          "notNull": false,
          "default": "'{}'::jsonb"
        },
        "cached_at": {
          "name": "cached_at",
          "type": "timestamp with time zone",
          "primaryKey": false,
          "notNull": true,
          "default": "now()"
        },
        "expires_at": {
          "name": "expires_at",
          "type": "timestamp with time zone",
          "primaryKey": false,
          "notNull": false
        }
      },
      "indexes": {
        "meetings_cache_unique": {
          "name": "meetings_cache_unique",
          "columns": [
            {
              "expression": "user_id",
              "isExpression": false,
              "asc": true,
              "nulls": "last"
            },
            {
              "expression": "platform",
              "isExpression": false,
              "asc": true,
              "nulls": "last"
            },
            {
              "expression": "platform_meeting_id",
              "isExpression": false,
              "asc": true,
              "nulls": "last"
            }
          ],
          "isUnique": true,
          "concurrently": false,
          "method": "btree",
          "with": {}
        },
        "meetings_cache_user_idx": {
          "name": "meetings_cache_user_idx",
          "columns": [
            {
              "expression": "user_id",
              "isExpression": false,
              "asc": true,
              "nulls": "last"
            }
          ],
          "isUnique": false,
          "concurrently": false,
          "method": "btree",
          "with": {}
        },
        "meetings_cache_start_time_idx": {
          "name": "meetings_cache_start_time_idx",
          "columns": [
            {
              "expression": "start_time",
              "isExpression": false,
              "asc": true,
              "nulls": "last"
            }
          ],
          "isUnique": false,
          "concurrently": false,
          "method": "btree",
          "with": {}
        }
      },
      "foreignKeys": {
        "meetings_cache_user_id_users_id_fk": {
          "name": "meetings_cache_user_id_users_id_fk",
          "tableFrom": "meetings_cache",
          "tableTo": "users",
          "columnsFrom": [
            "user_id"
          ],
          "columnsTo": [
            "id"
          ],
          "onDelete": "cascade",
          "onUpdate": "no action"
        }
      },
      "compositePrimaryKeys": {},
      "uniqueConstraints": {},
      "policies": {},
      "checkConstraints": {},
      "isRLSEnabled": false
    },
    "public.oauth_access_tokens": {
      "name": "oauth_access_tokens",
      "schema": "",
      "columns": {
        "id": {
          "name": "id",
          "type": "uuid",
          "primaryKey": true,
          "notNull": true,
          "default": "gen_random_uuid()"
        },
        "jti": {
          "name": "jti",
          "type": "varchar(256)",
          "primaryKey": false,
          "notNull": true
        },
        "client_id": {
          "name": "client_id",
          "type": "varchar(256)",
          "primaryKey": false,
          "notNull": true
        },
        "user_id": {
          "name": "user_id",
          "type": "uuid",
          "primaryKey": false,
          "notNull": true
        },
        "scope": {
          "name": "scope",
          "type": "text",
          "primaryKey": false,
          "notNull": true
        },
        "expires_at": {
          "name": "expires_at",
          "type": "timestamp with time zone",
          "primaryKey": false,
          "notNull": true
        },
        "revoked_at": {
          "name": "revoked_at",
          "type": "timestamp with time zone",
          "primaryKey": false,
          "notNull": false
        },
        "created_at": {
          "name": "created_at",
          "type": "timestamp with time zone",
          "primaryKey": false,
          "notNull": true,
          "default": "now()"
        }
      },
      "indexes": {
        "oauth_access_tokens_jti_unique": {
          "name": "oauth_access_tokens_jti_unique",
          "columns": [
            {
              "expression": "jti",
              "isExpression": false,
              "asc": true,
              "nulls": "last"
            }
          ],
          "isUnique": true,
          "concurrently": false,
          "method": "btree",
          "with": {}
        },
        "oauth_access_tokens_user_idx": {
          "name": "oauth_access_tokens_user_idx",
          "columns": [
            {
              "expression": "user_id",
              "isExpression": false,
              "asc": true,
              "nulls": "last"
            }
          ],
          "isUnique": false,
          "concurrently": false,
          "method": "btree",
          "with": {}
        }
      },
      "foreignKeys": {
        "oauth_access_tokens_user_id_users_id_fk": {
          "name": "oauth_access_tokens_user_id_users_id_fk",
          "tableFrom": "oauth_access_tokens",
          "tableTo": "users",
          "columnsFrom": [
            "user_id"
          ],
          "columnsTo": [
            "id"
          ],
          "onDelete": "cascade",
          "onUpdate": "no action"
        }
      },
      "compositePrimaryKeys": {},
      "uniqueConstraints": {},
      "policies": {},
      "checkConstraints": {},
      "isRLSEnabled": false
    },
    "public.oauth_authorization_codes": {
      "name": "oauth_authorization_codes",
      "schema": "",
      "columns": {
        "id": {
          "name": "id",
          "type": "uuid",
          "primaryKey": true,
          "notNull": true,
          "default": "gen_random_uuid()"
        },
        "code": {
          "name": "code",
          "type": "varchar(256)",
          "primaryKey": false,
          "notNull": true
        },
        "client_id": {
          "name": "client_id",
          "type": "varchar(256)",
          "primaryKey": false,
          "notNull": true
        },
        "user_id": {
          "name": "user_id",
          "type": "uuid",
          "primaryKey": false,
          "notNull": true
        },
        "redirect_uri": {
          "name": "redirect_uri",
          "type": "text",
          "primaryKey": false,
          "notNull": true
        },
        "scope": {
          "name": "scope",
          "type": "text",
          "primaryKey": false,
          "notNull": true
        },
        "code_challenge": {
          "name": "code_challenge",
          "type": "varchar(256)",
          "primaryKey": false,
          "notNull": true
        },
        "code_challenge_method": {
          "name": "code_challenge_method",
          "type": "varchar(10)",
          "primaryKey": false,
          "notNull": true,
          "default": "'S256'"
        },
        "nonce": {
          "name": "nonce",
          "type": "varchar(256)",
          "primaryKey": false,
          "notNull": false
        },
        "state": {
          "name": "state",
          "type": "varchar(256)",
          "primaryKey": false,
          "notNull": false
        },
        "expires_at": {
          "name": "expires_at",
          "type": "timestamp with time zone",
          "primaryKey": false,
          "notNull": true
        },
        "used_at": {
          "name": "used_at",
          "type": "timestamp with time zone",
          "primaryKey": false,
          "notNull": false
        },
        "created_at": {
          "name": "created_at",
          "type": "timestamp with time zone",
          "primaryKey": false,
          "notNull": true,
          "default": "now()"
        }
      },
      "indexes": {
        "oauth_authorization_codes_code_unique": {
          "name": "oauth_authorization_codes_code_unique",
          "columns": [
            {
              "expression": "code",
              "isExpression": false,
              "asc": true,
              "nulls": "last"
            }
          ],
          "isUnique": true,
          "concurrently": false,
          "method": "btree",
          "with": {}
        },
        "oauth_authorization_codes_expires_idx": {
          "name": "oauth_authorization_codes_expires_idx",
          "columns": [
            {
              "expression": "expires_at",
              "isExpression": false,
              "asc": true,
              "nulls": "last"
            }
          ],
          "isUnique": false,
          "concurrently": false,
          "method": "btree",
          "with": {}
        }
      },
      "foreignKeys": {
        "oauth_authorization_codes_user_id_users_id_fk": {
          "name": "oauth_authorization_codes_user_id_users_id_fk",
          "tableFrom": "oauth_authorization_codes",
          "tableTo": "users",
          "columnsFrom": [
            "user_id"
          ],
          "columnsTo": [
            "id"
          ],
          "onDelete": "cascade",
          "onUpdate": "no action"
        }
      },
      "compositePrimaryKeys": {},
      "uniqueConstraints": {},
      "policies": {},
      "checkConstraints": {},
      "isRLSEnabled": false
    },
    "public.oauth_clients": {
      "name": "oauth_clients",
      "schema": "",
      "columns": {
        "id": {
          "name": "id",
          "type": "uuid",
          "primaryKey": true,
          "notNull": true,
          "default": "gen_random_uuid()"
        },
        "client_id": {
          "name": "client_id",
          "type": "varchar(256)",
          "primaryKey": false,
          "notNull": true
        },
        "client_secret": {
          "name": "client_secret",
          "type": "text",
          "primaryKey": false,
          "notNull": false
        },
        "client_name": {
          "name": "client_name",
          "type": "varchar(256)",
          "primaryKey": false,
          "notNull": true
        },
        "client_description": {
          "name": "client_description",
          "type": "text",
          "primaryKey": false,
          "notNull": false
        },
        "client_uri": {
          "name": "client_uri",
          "type": "text",
          "primaryKey": false,
          "notNull": false
        },
        "logo_uri": {
          "name": "logo_uri",
          "type": "text",
          "primaryKey": false,
          "notNull": false
        },
        "redirect_uris": {
          "name": "redirect_uris",
          "type": "jsonb",
          "primaryKey": false,
          "notNull": true
        },
        "allowed_origins": {
          "name": "allowed_origins",
          "type": "jsonb",
          "primaryKey": false,
          "notNull": false
        },
        "client_type": {
          "name": "client_type",
          "type": "varchar(50)",
          "primaryKey": false,
          "notNull": true,
          "default": "'confidential'"
        },
        "grant_types": {
          "name": "grant_types",
          "type": "jsonb",
          "primaryKey": false,
          "notNull": true,
          "default": "'[\"authorization_code\",\"refresh_token\"]'::jsonb"
        },
        "response_types": {
          "name": "response_types",
          "type": "jsonb",
          "primaryKey": false,
          "notNull": true,
          "default": "'[\"code\"]'::jsonb"
        },
        "allowed_scopes": {
          "name": "allowed_scopes",
          "type": "text",
          "primaryKey": false,
          "notNull": true,
          "default": "'openid profile email meetings:read meetings:summary tasks:write'"
        },
        "registration_access_token": {
          "name": "registration_access_token",
          "type": "text",
          "primaryKey": false,
          "notNull": false
        },
        "is_active": {
          "name": "is_active",
          "type": "boolean",
          "primaryKey": false,
          "notNull": false,
          "default": true
        },
        "created_at": {
          "name": "created_at",
          "type": "timestamp with time zone",
          "primaryKey": false,
          "notNull": true,
          "default": "now()"
        },
        "updated_at": {
          "name": "updated_at",
          "type": "timestamp with time zone",
          "primaryKey": false,
          "notNull": true,
          "default": "now()"
        }
      },
      "indexes": {
        "oauth_clients_client_id_unique": {
          "name": "oauth_clients_client_id_unique",
          "columns": [
            {
              "expression": "client_id",
              "isExpression": false,
              "asc": true,
              "nulls": "last"
            }
          ],
          "isUnique": true,
          "concurrently": false,
          "method": "btree",
          "with": {}
        }
      },
      "foreignKeys": {},
      "compositePrimaryKeys": {},
      "uniqueConstraints": {},
      "policies": {},
      "checkConstraints": {},
      "isRLSEnabled": false
    },
    "public.oauth_refresh_tokens": {
      "name": "oauth_refresh_tokens",
      "schema": "",
      "columns": {
        "id": {
          "name": "id",
          "type": "uuid",
          "primaryKey": true,
          "notNull": true,
          "default": "gen_random_uuid()"
        },
        "jti": {
          "name": "jti",
          "type": "varchar(256)",
          "primaryKey": false,
          "notNull": true
        },
        "client_id": {
          "name": "client_id",
          "type": "varchar(256)",
          "primaryKey": false,
          "notNull": true
        },
        "user_id": {
          "name": "user_id",
          "type": "uuid",
          "primaryKey": false,
          "notNull": true
        },
        "scope": {
          "name": "scope",
          "type": "text",
          "primaryKey": false,
          "notNull": true
        },
        "parent_jti": {
          "name": "parent_jti",
          "type": "varchar(256)",
          "primaryKey": false,
          "notNull": false
        },
        "expires_at": {
          "name": "expires_at",
          "type": "timestamp with time zone",
          "primaryKey": false,
          "notNull": true
        },
        "revoked_at": {
          "name": "revoked_at",
          "type": "timestamp with time zone",
          "primaryKey": false,
          "notNull": false
        },
        "last_used_at": {
          "name": "last_used_at",
          "type": "timestamp with time zone",
          "primaryKey": false,
          "notNull": false
        },
        "created_at": {
          "name": "created_at",
          "type": "timestamp with time zone",
          "primaryKey": false,
          "notNull": true,
          "default": "now()"
        }
      },
      "indexes": {
        "oauth_refresh_tokens_jti_unique": {
          "name": "oauth_refresh_tokens_jti_unique",
          "columns": [
            {
              "expression": "jti",
              "isExpression": false,
              "asc": true,
              "nulls": "last"
            }
          ],
          "isUnique": true,
          "concurrently": false,
          "method": "btree",
          "with": {}
        },
        "oauth_refresh_tokens_user_idx": {
          "name": "oauth_refresh_tokens_user_idx",
          "columns": [
            {
              "expression": "user_id",
              "isExpression": false,
              "asc": true,
              "nulls": "last"
            }
          ],
          "isUnique": false,
          "concurrently": false,
          "method": "btree",
          "with": {}
        }
      },
      "foreignKeys": {
        "oauth_refresh_tokens_user_id_users_id_fk": {
          "name": "oauth_refresh_tokens_user_id_users_id_fk",
          "tableFrom": "oauth_refresh_tokens",
          "tableTo": "users",
          "columnsFrom": [
            "user_id"
          ],
          "columnsTo": [
            "id"
          ],
          "onDelete": "cascade",
          "onUpdate": "no action"
        }
      },
      "compositePrimaryKeys": {},
      "uniqueConstraints": {},
      "policies": {},
      "checkConstraints": {},
      "isRLSEnabled": false
    },
    "public.oauth_states": {
      "name": "oauth_states",
      "schema": "",
      "columns": {
        "id": {
          "name": "id",
          "type": "uuid",
          "primaryKey": true,
          "notNull": true,
          "default": "gen_random_uuid()"
        },
        "state": {
          "name": "state",
          "type": "varchar(256)",
          "primaryKey": false,
          "notNull": true
        },
        "platform": {
          "name": "platform",
          "type": "platform",
          "typeSchema": "public",
          "primaryKey": false,
          "notNull": true
        },
        "user_id": {
          "name": "user_id",
          "type": "uuid",
          "primaryKey": false,
          "notNull": false
        },
        "code_verifier": {
          "name": "code_verifier",
          "type": "varchar(256)",
          "primaryKey": false,
          "notNull": true
        },
        "redirect_after": {
          "name": "redirect_after",
          "type": "text",
          "primaryKey": false,
          "notNull": false
        },
        "metadata": {
          "name": "metadata",
          "type": "jsonb",
          "primaryKey": false,
          "notNull": false,
          "default": "'{}'::jsonb"
        },
        "expires_at": {
          "name": "expires_at",
          "type": "timestamp with time zone",
          "primaryKey": false,
          "notNull": true
        },
        "used_at": {
          "name": "used_at",
          "type": "timestamp with time zone",
          "primaryKey": false,
          "notNull": false
        },
        "created_at": {
          "name": "created_at",
          "type": "timestamp with time zone",
          "primaryKey": false,
          "notNull": true,
          "default": "now()"
        }
      },
      "indexes": {
        "oauth_states_state_unique": {
          "name": "oauth_states_state_unique",
          "columns": [
            {
              "expression": "state",
              "isExpression": false,
              "asc": true,
              "nulls": "last"
            }
          ],
          "isUnique": true,
          "concurrently": false,
          "method": "btree",
          "with": {}
        },
        "oauth_states_expires_idx": {
          "name": "oauth_states_expires_idx",
          "columns": [
            {
              "expression": "expires_at",
              "isExpression": false,
              "asc": true,
              "nulls": "last"
            }
          ],
          "isUnique": false,
          "concurrently": false,
          "method": "btree",
          "with": {}
        }
      },
      "foreignKeys": {
        "oauth_states_user_id_users_id_fk": {
          "name": "oauth_states_user_id_users_id_fk",
          "tableFrom": "oauth_states",
          "tableTo": "users",
          "columnsFrom": [
            "user_id"
          ],
          "columnsTo": [
            "id"
          ],
          "onDelete": "cascade",
          "onUpdate": "no action"
        }
      },
      "compositePrimaryKeys": {},
      "uniqueConstraints": {},
      "policies": {},
      "checkConstraints": {},
      "isRLSEnabled": false
    },
    "public.oauth_user_consents": {
      "name": "oauth_user_consents",
      "schema": "",
      "columns": {
        "id": {
          "name": "id",
          "type": "uuid",
          "primaryKey": true,
          "notNull": true,
          "default": "gen_random_uuid()"
        },
        "user_id": {
          "name": "user_id",
          "type": "uuid",
          "primaryKey": false,
          "notNull": true
        },
        "client_id": {
          "name": "client_id",
          "type": "varchar(256)",
          "primaryKey": false,
          "notNull": true
        },
        "scope": {
          "name": "scope",
          "type": "text",
          "primaryKey": false,
          "notNull": true
        },
        "consented_at": {
          "name": "consented_at",
          "type": "timestamp with time zone",
          "primaryKey": false,
          "notNull": true,
          "default": "now()"
        },
        "revoked_at": {
          "name": "revoked_at",
          "type": "timestamp with time zone",
          "primaryKey": false,
          "notNull": false
        }
      },
      "indexes": {
        "oauth_user_consents_user_client_unique": {
          "name": "oauth_user_consents_user_client_unique",
          "columns": [
            {
              "expression": "user_id",
              "isExpression": false,
              "asc": true,
              "nulls": "last"
            },
            {
              "expression": "client_id",
              "isExpression": false,
              "asc": true,
              "nulls": "last"
            }
          ],
          "isUnique": true,
          "concurrently": false,
          "method": "btree",
          "with": {}
        }
      },
      "foreignKeys": {
        "oauth_user_consents_user_id_users_id_fk": {
          "name": "oauth_user_consents_user_id_users_id_fk",
          "tableFrom": "oauth_user_consents",
          "tableTo": "users",
          "columnsFrom": [
            "user_id"
          ],
          "columnsTo": [
            "id"
          ],
          "onDelete": "cascade",
          "onUpdate": "no action"
        }
      },
      "compositePrimaryKeys": {},
      "uniqueConstraints": {},
      "policies": {},
      "checkConstraints": {},
      "isRLSEnabled": false
    },
    "public.organizations": {
      "name": "organizations",
      "schema": "",
      "columns": {
        "id": {
          "name": "id",
          "type": "uuid",
          "primaryKey": true,
          "notNull": true,
          "default": "gen_random_uuid()"
        },
        "name": {
          "name": "name",
          "type": "varchar(256)",
          "primaryKey": false,
          "notNull": true
        },
        "slug": {
          "name": "slug",
          "type": "varchar(100)",
          "primaryKey": false,
          "notNull": true
        },
        "domain": {
          "name": "domain",
          "type": "varchar(256)",
          "primaryKey": false,
          "notNull": false
        },
        "sso_enabled": {
          "name": "sso_enabled",
          "type": "boolean",
          "primaryKey": false,
          "notNull": false,
          "default": false
        },
        "sso_provider": {
          "name": "sso_provider",
          "type": "varchar(50)",
          "primaryKey": false,
          "notNull": false
        },
        "sso_config": {
          "name": "sso_config",
          "type": "jsonb",
          "primaryKey": false,
          "notNull": false
        },
        "settings": {
          "name": "settings",
          "type": "jsonb",
          "primaryKey": false,
          "notNull": false,
          "default": "'{}'::jsonb"
        },
        "is_active": {
          "name": "is_active",
          "type": "boolean",
          "primaryKey": false,
          "notNull": false,
          "default": true
        },
        "created_at": {
          "name": "created_at",
          "type": "timestamp with time zone",
          "primaryKey": false,
          "notNull": true,
          "default": "now()"
        },
        "updated_at": {
          "name": "updated_at",
          "type": "timestamp with time zone",
          "primaryKey": false,
          "notNull": true,
          "default": "now()"
        }
      },
      "indexes": {
        "organizations_slug_unique": {
          "name": "organizations_slug_unique",
          "columns": [
            {
              "expression": "slug",
              "isExpression": false,
              "asc": true,
              "nulls": "last"
            }
          ],
          "isUnique": true,
          "concurrently": false,
          "method": "btree",
          "with": {}
        },
        "organizations_domain_idx": {
          "name": "organizations_domain_idx",
          "columns": [
            {
              "expression": "domain",
              "isExpression": false,
              "asc": true,
              "nulls": "last"
            }
          ],
          "isUnique": false,
          "concurrently": false,
          "method": "btree",
          "with": {}
        }
      },
      "foreignKeys": {},
      "compositePrimaryKeys": {},
      "uniqueConstraints": {},
      "policies": {},
      "checkConstraints": {},
      "isRLSEnabled": false
    },
    "public.platform_connections": {
      "name": "platform_connections",
      "schema": "",
      "columns": {
        "id": {
          "name": "id",
          "type": "uuid",
          "primaryKey": true,
          "notNull": true,
          "default": "gen_random_uuid()"
        },
        "user_id": {
          "name": "user_id",
          "type": "uuid",
          "primaryKey": false,
          "notNull": true
        },
        "platform": {
          "name": "platform",
          "type": "platform",
          "typeSchema": "public",
          "primaryKey": false,
          "notNull": true
        },
        "platform_category": {
          "name": "platform_category",
          "type": "platform_category",
          "typeSchema": "public",
          "primaryKey": false,
          "notNull": true
        },
        "platform_user_id": {
          "name": "platform_user_id",
          "type": "varchar(256)",
          "primaryKey": false,
          "notNull": false
        },
        "platform_email": {
          "name": "platform_email",
          "type": "varchar(320)",
          "primaryKey": false,
          "notNull": false
        },
        "platform_display_name": {
          "name": "platform_display_name",
          "type": "varchar(256)",
          "primaryKey": false,
          "notNull": false
        },
        "access_token": {
          "name": "access_token",
          "type": "text",
          "primaryKey": false,
          "notNull": true
        },
        "refresh_token": {
          "name": "refresh_token",
          "type": "text",
          "primaryKey": false,
          "notNull": false
        },
        "token_type": {
          "name": "token_type",
          "type": "varchar(50)",
          "primaryKey": false,
          "notNull": false,
          "default": "'Bearer'"
        },
        "scope": {
          "name": "scope",
          "type": "text",
          "primaryKey": false,
          "notNull": false
        },
        "expires_at": {
          "name": "expires_at",
          "type": "timestamp with time zone",
          "primaryKey": false,
          "notNull": false
        },
        "is_default": {
          "name": "is_default",
          "type": "boolean",
          "primaryKey": false,
          "notNull": false,
          "default": false
        },
        "is_active": {
          "name": "is_active",
          "type": "boolean",
          "primaryKey": false,
          "notNull": false,
          "default": true
        },
        "connected_at": {
          "name": "connected_at",
          "type": "timestamp with time zone",
          "primaryKey": false,
          "notNull": true,
          "default": "now()"
        },
        "updated_at": {
          "name": "updated_at",
          "type": "timestamp with time zone",
          "primaryKey": false,
          "notNull": true,
          "default": "now()"
        },
        "last_used_at": {
          "name": "last_used_at",
          "type": "timestamp with time zone",
          "primaryKey": false,
          "notNull": false
        },
        "metadata": {
          "name": "metadata",
          "type": "jsonb",
          "primaryKey": false,
          "notNull": false,
          "default": "'{}'::jsonb"
        }
      },
      "indexes": {
        "platform_connections_user_platform_unique": {
          "name": "platform_connections_user_platform_unique",
          "columns": [
            {
              "expression": "user_id",
              "isExpression": false,
              "asc": true,
              "nulls": "last"
            },
            {
              "expression": "platform",
              "isExpression": false,
              "asc": true,
              "nulls": "last"
            }
          ],
          "isUnique": true,
          "concurrently": false,
          "method": "btree",
          "with": {}
        },
        "platform_connections_user_idx": {
          "name": "platform_connections_user_idx",
          "columns": [
            {
              "expression": "user_id",
              "isExpression": false,
              "asc": true,
              "nulls": "last"
            }
          ],
          "isUnique": false,
          "concurrently": false,
          "method": "btree",
          "with": {}
        },
        "platform_connections_platform_idx": {
          "name": "platform_connections_platform_idx",
          "columns": [
            {
              "expression": "platform",
              "isExpression": false,
              "asc": true,
              "nulls": "last"
            }
          ],
          "isUnique": false,
          "concurrently": false,
          "method": "btree",
          "with": {}
        }
      },
      "foreignKeys": {
        "platform_connections_user_id_users_id_fk": {
          "name": "platform_connections_user_id_users_id_fk",
          "tableFrom": "platform_connections",
          "tableTo": "users",
          "columnsFrom": [
            "user_id"
          ],
          "columnsTo": [
            "id"
          ],
          "onDelete": "cascade",
          "onUpdate": "no action"
        }
      },
      "compositePrimaryKeys": {},
      "uniqueConstraints": {},
      "policies": {},
      "checkConstraints": {},
      "isRLSEnabled": false
    },
    "public.platform_destinations": {
      "name": "platform_destinations",
      "schema": "",
      "columns": {
        "id": {
          "name": "id",
          "type": "uuid",
          "primaryKey": true,
          "notNull": true,
          "default": "gen_random_uuid()"
        },
        "connection_id": {
          "name": "connection_id",
          "type": "uuid",
          "primaryKey": false,
          "notNull": true
        },
        "destination_type": {
          "name": "destination_type",
          "type": "varchar(50)",
          "primaryKey": false,
          "notNull": true
        },
        "destination_id": {
          "name": "destination_id",
          "type": "varchar(256)",
          "primaryKey": false,
          "notNull": true
        },
        "destination_name": {
          "name": "destination_name",
          "type": "varchar(256)",
          "primaryKey": false,
          "notNull": true
        },
        "parent_destination_id": {
          "name": "parent_destination_id",
          "type": "uuid",
          "primaryKey": false,
          "notNull": false
        },
        "is_default": {
          "name": "is_default",
          "type": "boolean",
          "primaryKey": false,
          "notNull": false,
          "default": false
        },
        "metadata": {
          "name": "metadata",
          "type": "jsonb",
          "primaryKey": false,
          "notNull": false,
          "default": "'{}'::jsonb"
        },
        "created_at": {
          "name": "created_at",
          "type": "timestamp with time zone",
          "primaryKey": false,
          "notNull": true,
          "default": "now()"
        },
        "updated_at": {
          "name": "updated_at",
          "type": "timestamp with time zone",
          "primaryKey": false,
          "notNull": true,
          "default": "now()"
        }
      },
      "indexes": {
        "platform_destinations_connection_idx": {
          "name": "platform_destinations_connection_idx",
          "columns": [
            {
              "expression": "connection_id",
              "isExpression": false,
              "asc": true,
              "nulls": "last"
            }
          ],
          "isUnique": false,
          "concurrently": false,
          "method": "btree",
          "with": {}
        },
        "platform_destinations_unique": {
          "name": "platform_destinations_unique",
          "columns": [
            {
              "expression": "connection_id",
              "isExpression": false,
              "asc": true,
              "nulls": "last"
            },
            {
              "expression": "destination_type",
              "isExpression": false,
              "asc": true,
              "nulls": "last"
            },
            {
              "expression": "destination_id",
              "isExpression": false,
              "asc": true,
              "nulls": "last"
            }
          ],
          "isUnique": true,
          "concurrently": false,
          "method": "btree",
          "with": {}
        }
      },
      "foreignKeys": {
        "platform_destinations_connection_id_platform_connections_id_fk": {
          "name": "platform_destinations_connection_id_platform_connections_id_fk",
          "tableFrom": "platform_destinations",
          "tableTo": "platform_connections",
          "columnsFrom": [
            "connection_id"
          ],
          "columnsTo": [
            "id"
          ],
          "onDelete": "cascade",
          "onUpdate": "no action"
        }
      },
      "compositePrimaryKeys": {},
      "uniqueConstraints": {},
      "policies": {},
      "checkConstraints": {},
      "isRLSEnabled": false
    },
    "public.user_preferences": {
      "name": "user_preferences",
      "schema": "",
      "columns": {
        "user_id": {
          "name": "user_id",
          "type": "uuid",
          "primaryKey": true,
          "notNull": true
        },
        "default_meeting_platform": {
          "name": "default_meeting_platform",
          "type": "platform",
          "typeSchema": "public",
          "primaryKey": false,
          "notNull": false
        },
        "auto_summarize": {
          "name": "auto_summarize",
          "type": "boolean",
          "primaryKey": false,
          "notNull": false,
          "default": false
        },
        "summary_language": {
          "name": "summary_language",
          "type": "varchar(10)",
          "primaryKey": false,
          "notNull": false,
          "default": "'en'"
        },
        "default_task_platform": {
          "name": "default_task_platform",
          "type": "platform",
          "typeSchema": "public",
          "primaryKey": false,
          "notNull": false
        },
        "auto_create_tasks": {
          "name": "auto_create_tasks",
          "type": "boolean",
          "primaryKey": false,
          "notNull": false,
          "default": false
        },
        "default_email_tone": {
          "name": "default_email_tone",
          "type": "varchar(50)",
          "primaryKey": false,
          "notNull": false,
          "default": "'professional'"
        },
        "email_signature": {
          "name": "email_signature",
          "type": "text",
          "primaryKey": false,
          "notNull": false
        },
        "summary_style": {
          "name": "summary_style",
          "type": "varchar(50)",
          "primaryKey": false,
          "notNull": false,
          "default": "'concise'"
        },
        "include_action_items": {
          "name": "include_action_items",
          "type": "boolean",
          "primaryKey": false,
          "notNull": false,
          "default": true
        },
        "include_key_decisions": {
          "name": "include_key_decisions",
          "type": "boolean",
          "primaryKey": false,
          "notNull": false,
          "default": true
        },
        "retain_transcripts_hours": {
          "name": "retain_transcripts_hours",
          "type": "integer",
          "primaryKey": false,
          "notNull": false,
          "default": 0
        },
        "allow_analytics": {
          "name": "allow_analytics",
          "type": "boolean",
          "primaryKey": false,
          "notNull": false,
          "default": true
        },
        "timezone": {
          "name": "timezone",
          "type": "varchar(64)",
          "primaryKey": false,
          "notNull": false,
          "default": "'America/Chicago'"
        },
        "additional_settings": {
          "name": "additional_settings",
          "type": "jsonb",
          "primaryKey": false,
          "notNull": false,
          "default": "'{}'::jsonb"
        },
        "updated_at": {
          "name": "updated_at",
          "type": "timestamp with time zone",
          "primaryKey": false,
          "notNull": true,
          "default": "now()"
        }
      },
      "indexes": {},
      "foreignKeys": {
        "user_preferences_user_id_users_id_fk": {
          "name": "user_preferences_user_id_users_id_fk",
          "tableFrom": "user_preferences",
          "tableTo": "users",
          "columnsFrom": [
            "user_id"
          ],
          "columnsTo": [
            "id"
          ],
          "onDelete": "cascade",
          "onUpdate": "no action"
        }
      },
      "compositePrimaryKeys": {},
      "uniqueConstraints": {},
      "policies": {},
      "checkConstraints": {},
      "isRLSEnabled": false
    },
    "public.users": {
      "name": "users",
      "schema": "",
      "columns": {
        "id": {
          "name": "id",
          "type": "uuid",
          "primaryKey": true,
          "notNull": true,
          "default": "gen_random_uuid()"
        },
        "email": {
          "name": "email",
          "type": "varchar(320)",
          "primaryKey": false,
          "notNull": true
        },
        "email_verified": {
          "name": "email_verified",
          "type": "boolean",
          "primaryKey": false,
          "notNull": false,
          "default": false
        },
        "name": {
          "name": "name",
          "type": "varchar(256)",
          "primaryKey": false,
          "notNull": false
        },
        "avatar_url": {
          "name": "avatar_url",
          "type": "text",
          "primaryKey": false,
          "notNull": false
        },
        "google_id": {
          "name": "google_id",
          "type": "varchar(256)",
          "primaryKey": false,
          "notNull": false
        },
        "microsoft_id": {
          "name": "microsoft_id",
          "type": "varchar(256)",
          "primaryKey": false,
          "notNull": false
        },
        "is_active": {
          "name": "is_active",
          "type": "boolean",
          "primaryKey": false,
          "notNull": false,
          "default": true
        },
        "organization_id": {
          "name": "organization_id",
          "type": "uuid",
          "primaryKey": false,
          "notNull": false
        },
        "created_at": {
          "name": "created_at",
          "type": "timestamp with time zone",
          "primaryKey": false,
          "notNull": true,
          "default": "now()"
        },
        "updated_at": {
          "name": "updated_at",
          "type": "timestamp with time zone",
          "primaryKey": false,
          "notNull": true,
          "default": "now()"
        },
        "last_login_at": {
          "name": "last_login_at",
          "type": "timestamp with time zone",
          "primaryKey": false,
          "notNull": false
        }
      },
      "indexes": {
        "users_email_unique": {
          "name": "users_email_unique",
          "columns": [
            {
              "expression": "email",
              "isExpression": false,
              "asc": true,
              "nulls": "last"
            }
          ],
          "isUnique": true,
          "concurrently": false,
          "method": "btree",
          "with": {}
        },
        "users_google_id_idx": {
          "name": "users_google_id_idx",
          "columns": [
            {
              "expression": "google_id",
              "isExpression": false,
              "asc": true,
              "nulls": "last"
            }
          ],
          "isUnique": false,
          "concurrently": false,
          "method": "btree",
          "with": {}
        },
        "users_microsoft_id_idx": {
          "name": "users_microsoft_id_idx",
          "columns": [
            {
              "expression": "microsoft_id",
              "isExpression": false,
              "asc": true,
              "nulls": "last"
            }
          ],
          "isUnique": false,
          "concurrently": false,
          "method": "btree",
          "with": {}
        }
      },
      "foreignKeys": {},
      "compositePrimaryKeys": {},
      "uniqueConstraints": {},
      "policies": {},
      "checkConstraints": {},
      "isRLSEnabled": false
    }
  },
  "enums": {
    "public.platform_category": {
      "name": "platform_category",
      "schema": "public",
      "values": [
        "meetings",
        "tasks",
        "email",
        "communication"
      ]
    },
    "public.platform": {
      "name": "platform",
      "schema": "public",
      "values": [
        "zoom",
        "teams",
        "meet",
        "webex",
        "asana",
        "jira",
        "notion",
        "linear",
        "trello",
        "monday",
        "slack",
        "gmail",
        "outlook"
      ]
    }
  },
  "schemas": {},
  "sequences": {},
  "roles": {},
  "policies": {},
  "views": {},
  "_meta": {
    "columns": {},
    "schemas": {},
    "tables": {}
  }
}